backlooper/__init__.py
backlooper/__main__.py
backlooper/_clicktrack.py
backlooper/audio.py
backlooper/config.py
backlooper/session.py
backlooper/striped_storage.py
backlooper/samples/hi_hat.wav
backlooper/tests/__init__.py
backlooper/tests/test_striped_storage.py
backlooper-0.2.1.dist-info/licenses/LICENSE
backlooper-0.2.1.dist-info/METADATA
backlooper-0.2.1.dist-info/WHEEL
backlooper-0.2.1.dist-info/top_level.txt
backlooper-0.2.1.dist-info/RECORD
