Metadata-Version: 2.4
Name: backlooper
Version: 0.2.1
Summary: Backlooper.app is a looper that allows you to decide to loop a few bars after you played them
Home-page: https://github.com/spmvg/backlooper_backend
Author: Steven van Gemert
Author-email: steven@vangemert.dev
Requires-Python: >=3.8
License-File: LICENSE
Requires-Dist: sounddevice
Requires-Dist: numpy
Requires-Dist: matplotlib
Requires-Dist: pandas
Requires-Dist: scipy
Requires-Dist: websockets
Dynamic: license-file
